[
  {
    "degree": "Master of Science in Data Science",
    "institution": "ABC University",
    "duration": "2021 - 2023",
    "image": "/assets/education/avatar.png",
    "description": [
      "Specialized in advanced machine learning, big data, and AI methodologies.",
      "Focused on predictive analytics and real-time data processing techniques.",
      "Worked on various data-driven research projects and thesis involving AI and ML.",
      "Graduated with honors in a cohort of 40+ students."
    ]
  },
  {
    "degree": "Bachelor of Science in Computer Science",
    "institution": "XYZ University",
    "duration": "2017 - 2021",
    "image": "/assets/education/avatar.png",
    "description": [
      "Focused on software development, AI, and data science.",
      "Built multiple projects in software engineering and machine learning.",
      "Graduated with honors and completed internship in a leading tech company.",
      "Worked on several capstone projects related to web development and AI."
    ]
  }
]